rtui2/__init__.py
rtui2/app/__init__.py
rtui2/app/inspect.py
rtui2/cli.py
rtui2/event.py
rtui2/ros/__init__.py
rtui2/ros/client.py
rtui2/ros/entity.py
rtui2/ros/exception.py
rtui2/ros/interface/__init__.py
rtui2/ros/interface/base.py
rtui2/ros/interface/ros2.py
rtui2/screens.py
rtui2/utility/__init__.py
rtui2/utility/hisotry.py
rtui2/widgets/__init__.py
rtui2/widgets/info_panel.py
rtui2/widgets/list_panel.py
rtui2/widgets/type_definition.py
rtui2-0.1.0.dist-info/LICENSE
rtui2-0.1.0.dist-info/METADATA
rtui2-0.1.0.dist-info/NOTICE
rtui2-0.1.0.dist-info/WHEEL
rtui2-0.1.0.dist-info/entry_points.txt
rtui2-0.1.0.dist-info/RECORD
