Metadata-Version: 2.3
Name: rtui2
Version: 0.1.0
Summary: A TUI tool for ROS 2 Topic/Node debugging
License: Apache-2.0
Author: Daisuke Sato
Author-email: daisuke.sato@whill.inc
Requires-Python: >=3.10,<4.0
Classifier: License :: OSI Approved :: Apache Software License
Classifier: Programming Language :: Python :: 3
Classifier: Programming Language :: Python :: 3.10
Classifier: Programming Language :: Python :: 3.11
Classifier: Programming Language :: Python :: 3.12
Classifier: Programming Language :: Python :: 3.13
Requires-Dist: PyYAML (>=6.0.1,<7.0.0)
Requires-Dist: argcomplete (>=3.6.2,<4.0.0)
Requires-Dist: click (>=8.1.3,<9.0.0)
Requires-Dist: netifaces (>=0.11.0,<0.12.0)
Requires-Dist: numpy (>=1.23.0,<2.0.0)
Requires-Dist: textual (>=0.40,<0.41)
Requires-Dist: typing-extensions (>=4.3.0,<5.0.0)
Project-URL: Repository, https://github.com/whill-labs/rtui2
